tic_tac_toe_engine/__init__.py
tic_tac_toe_engine/engine.py
tic_tac_toe_engine/example.py
tic_tac_toe_engine/exceptions.py
tic_tac_toe_engine/position.py
tic_tac_toe_engine-0.1.7.dist-info/LICENCE
tic_tac_toe_engine-0.1.7.dist-info/METADATA
tic_tac_toe_engine-0.1.7.dist-info/WHEEL
tic_tac_toe_engine-0.1.7.dist-info/top_level.txt
tic_tac_toe_engine-0.1.7.dist-info/RECORD
