Metadata-Version: 2.1
Name: tic-tac-toe-engine
Version: 0.1.7
Summary: An implementation of the Tic Tac Toe game rules
Home-page: UNKNOWN
Author: Sebastian Mendoza
Author-email: <sebastian.mendoza.clases@gmail.com>
License: UNKNOWN
Keywords: python,tic-tac-toe,tictactoe,game,engine
Platform: UNKNOWN
Classifier: Development Status :: 2 - Pre-Alpha
Classifier: Intended Audience :: Developers
Classifier: Programming Language :: Python :: 3
Classifier: Operating System :: Unix
Classifier: Operating System :: MacOS :: MacOS X
Classifier: Operating System :: Microsoft :: Windows
License-File: LICENCE
